wafermap_plot/wafermap.py
wafermap_plot/models/defect_point.py
wafermap_plot-0.1.3.dist-info/LICENSE.txt
wafermap_plot-0.1.3.dist-info/METADATA
wafermap_plot-0.1.3.dist-info/WHEEL
wafermap_plot-0.1.3.dist-info/top_level.txt
wafermap_plot-0.1.3.dist-info/RECORD
