Metadata-Version: 2.1
Name: wafermap-plot
Version: 0.1.3
Summary: A project to plot wafermaps
Home-page: https://github.com/Impro02/wafermap-plot
Download-URL: https://github.com/Impro02/wafermap-plot/archive/refs/tags/0.1.3.tar.gz
Author: Maxime MARTIN
Author-email: maxime.martin02@hotmail.fr
License: MIT
Classifier: Development Status :: 3 - Alpha
Classifier: Intended Audience :: Developers
Classifier: License :: OSI Approved :: MIT License
Classifier: Programming Language :: Python :: 3
License-File: LICENSE.txt
Requires-Dist: numpy
Requires-Dist: matplotlib
Requires-Dist: colormath
